server.py
trellis_api/__init__.py
trellis_api/client.py
trellis_api/exceptions.py
trellis_api/models.py
trellis_mcp-0.1.2.dist-info/METADATA
trellis_mcp-0.1.2.dist-info/WHEEL
trellis_mcp-0.1.2.dist-info/entry_points.txt
trellis_mcp-0.1.2.dist-info/top_level.txt
trellis_mcp-0.1.2.dist-info/RECORD
