Metadata-Version: 2.4
Name: trellis-mcp
Version: 0.1.2
Summary: MCP (Model Control Protocol) integration for Trellis
Author-email: FishWoWater <dreamboy.gns@gmail.com>
License: MIT
Keywords: mcp,blender,3d,automation
Classifier: Development Status :: 3 - Alpha
Classifier: Intended Audience :: Developers
Classifier: License :: OSI Approved :: MIT License
Classifier: Programming Language :: Python :: 3
Classifier: Programming Language :: Python :: 3.10
Requires-Python: >=3.10
Requires-Dist: aiohttp>=3.11.13
Requires-Dist: mcp[cli]>=1.4.1
Provides-Extra: dev
